LICENSE
MANIFEST.in
README.md
setup.cfg
setup.py
qsnark_python_sdk/__init__.py
qsnark_python_sdk/main.py
qsnark_python_sdk.egg-info/PKG-INFO
qsnark_python_sdk.egg-info/SOURCES.txt
qsnark_python_sdk.egg-info/dependency_links.txt
qsnark_python_sdk.egg-info/requires.txt
qsnark_python_sdk.egg-info/top_level.txt
qsnark_python_sdk/api/__init__.py
qsnark_python_sdk/api/access_token.py
qsnark_python_sdk/api/account.py
qsnark_python_sdk/api/block.py
qsnark_python_sdk/api/contract.py
qsnark_python_sdk/api/transaction.py
qsnark_python_sdk/http/__init__.py
qsnark_python_sdk/http/request.py